task_similarity/__init__.py
task_similarity/constants.py
task_similarity/iou_similarity.py
task_similarity/parameter_selection.py
task_similarity/utils.py
hpo_task_similarity-0.1.1.dist-info/LICENSE
hpo_task_similarity-0.1.1.dist-info/METADATA
hpo_task_similarity-0.1.1.dist-info/WHEEL
hpo_task_similarity-0.1.1.dist-info/top_level.txt
hpo_task_similarity-0.1.1.dist-info/RECORD
